yatgl/__init__.py
yatgl/client.py
yatgl-1.0.6.dist-info/LICENSE
yatgl-1.0.6.dist-info/METADATA
yatgl-1.0.6.dist-info/WHEEL
yatgl-1.0.6.dist-info/top_level.txt
yatgl-1.0.6.dist-info/RECORD
