Metadata-Version: 2.1
Name: yatgl
Version: 1.0.6
Summary: An asynchronous NationStates Telegram API library.
Home-page: https://github.com/NotAName320/yatgl
Author: Nota
License: GPLv3
License-File: LICENSE
Requires-Dist: aiohttp[speedups]
Requires-Dist: beautifulsoup4
Requires-Dist: lxml
